{
  "plan_file": "docs/planning/advanced-segmentation-execution-plan.xml",
  "plan_version": "1.0",
  "execution_mode": "autonomous",
  "current_task_id": null,
  "current_phase": null,
  "inner_iteration": 0,
  "tasks": {
    "T0.1": {"status": "DONE", "type": "RED", "tests": 8},
    "T0.2": {"status": "DONE", "type": "GREEN"},
    "T0.3": {"status": "DONE", "type": "GREEN"},
    "T1.1": {"status": "DONE", "type": "RED", "tests": 7},
    "T1.2": {"status": "DONE", "type": "GREEN"},
    "T2.1": {"status": "DONE", "type": "RED", "tests": 8},
    "T2.2": {"status": "DONE", "type": "GREEN"},
    "T3.1": {"status": "DONE", "type": "RED", "tests": 8},
    "T3.2": {"status": "DONE", "type": "GREEN"},
    "T4.1": {"status": "DONE", "type": "RED", "tests": 6},
    "T4.2": {"status": "DONE", "type": "GREEN"},
    "T5.1": {"status": "DONE", "type": "RED", "tests": 6},
    "T5.2": {"status": "DONE", "type": "GREEN"},
    "T8.1": {"status": "DONE", "type": "RED", "tests": 6},
    "T8.2": {"status": "DONE", "type": "GREEN"},
    "T8.3": {"status": "DONE", "type": "GREEN"}
  },
  "convergence": {
    "reached": true,
    "tasks_done": 16,
    "tasks_total": 20,
    "tasks_stuck": 0
  },
  "session_task_count": 16,
  "session_inner_iterations": 7,
  "session_start": "2026-03-04T12:00:00Z"
}
