[
  {
    "fold": 0,
    "n_train": 46,
    "n_val": 24,
    "train_ids": [
      "mv01",
      "mv03",
      "mv04",
      "mv06",
      "mv07",
      "mv08",
      "mv09",
      "mv10",
      "mv12",
      "mv13",
      "mv17",
      "mv18",
      "mv19",
      "mv21",
      "mv22",
      "mv23",
      "mv24",
      "mv25",
      "mv28",
      "mv29",
      "mv30",
      "mv33",
      "mv34",
      "mv35",
      "mv36",
      "mv37",
      "mv39",
      "mv41",
      "mv42",
      "mv44",
      "mv47",
      "mv48",
      "mv49",
      "mv51",
      "mv52",
      "mv53",
      "mv56",
      "mv57",
      "mv59",
      "mv60",
      "mv63",
      "mv64",
      "mv65",
      "mv66",
      "mv67",
      "mv68"
    ],
    "val_ids": [
      "mv02",
      "mv05",
      "mv11",
      "mv14",
      "mv15",
      "mv16",
      "mv20",
      "mv26",
      "mv27",
      "mv31",
      "mv32",
      "mv38",
      "mv40",
      "mv43",
      "mv45",
      "mv46",
      "mv50",
      "mv54",
      "mv55",
      "mv58",
      "mv61",
      "mv62",
      "mv69",
      "mv70"
    ]
  },
  {
    "fold": 1,
    "n_train": 47,
    "n_val": 23,
    "train_ids": [
      "mv02",
      "mv04",
      "mv05",
      "mv07",
      "mv09",
      "mv10",
      "mv11",
      "mv12",
      "mv14",
      "mv15",
      "mv16",
      "mv17",
      "mv20",
      "mv23",
      "mv25",
      "mv26",
      "mv27",
      "mv28",
      "mv29",
      "mv31",
      "mv32",
      "mv33",
      "mv34",
      "mv35",
      "mv38",
      "mv40",
      "mv41",
      "mv42",
      "mv43",
      "mv44",
      "mv45",
      "mv46",
      "mv50",
      "mv52",
      "mv54",
      "mv55",
      "mv56",
      "mv57",
      "mv58",
      "mv59",
      "mv61",
      "mv62",
      "mv63",
      "mv65",
      "mv68",
      "mv69",
      "mv70"
    ],
    "val_ids": [
      "mv01",
      "mv03",
      "mv06",
      "mv08",
      "mv13",
      "mv18",
      "mv19",
      "mv21",
      "mv22",
      "mv24",
      "mv30",
      "mv36",
      "mv37",
      "mv39",
      "mv47",
      "mv48",
      "mv49",
      "mv51",
      "mv53",
      "mv60",
      "mv64",
      "mv66",
      "mv67"
    ]
  },
  {
    "fold": 2,
    "n_train": 47,
    "n_val": 23,
    "train_ids": [
      "mv01",
      "mv02",
      "mv03",
      "mv05",
      "mv06",
      "mv08",
      "mv11",
      "mv13",
      "mv14",
      "mv15",
      "mv16",
      "mv18",
      "mv19",
      "mv20",
      "mv21",
      "mv22",
      "mv24",
      "mv26",
      "mv27",
      "mv30",
      "mv31",
      "mv32",
      "mv36",
      "mv37",
      "mv38",
      "mv39",
      "mv40",
      "mv43",
      "mv45",
      "mv46",
      "mv47",
      "mv48",
      "mv49",
      "mv50",
      "mv51",
      "mv53",
      "mv54",
      "mv55",
      "mv58",
      "mv60",
      "mv61",
      "mv62",
      "mv64",
      "mv66",
      "mv67",
      "mv69",
      "mv70"
    ],
    "val_ids": [
      "mv04",
      "mv07",
      "mv09",
      "mv10",
      "mv12",
      "mv17",
      "mv23",
      "mv25",
      "mv28",
      "mv29",
      "mv33",
      "mv34",
      "mv35",
      "mv41",
      "mv42",
      "mv44",
      "mv52",
      "mv56",
      "mv57",
      "mv59",
      "mv63",
      "mv65",
      "mv68"
    ]
  }
]
